{
  "ids": [
    "america/ciudad_juarez"
  ],
  "tzif": {
    "posix": {
      "abbr": "MST",
      "offset": -25200,
      "transition": {
        "abbr": "MDT",
        "end": {
          "date": {
            "day": null,
            "kind": "MonthWeekDay",
            "mwd": [
              11,
              1,
              0
            ]
          },
          "time": 7200
        },
        "savings": 3600,
        "start": {
          "date": {
            "day": null,
            "kind": "MonthWeekDay",
            "mwd": [
              3,
              2,
              0
            ]
          },
          "time": 7200
        }
      }
    },
    "transition_types": [
      1,
      2,
      1,
      2,
      3,
      1,
      2,
      3,
      4,
      2,
      3,
      4,
      2,
      3,
      2,
      3,
      1,
      2,
      3,
      1,
      2,
      3,
      1,
      2,
      3,
      1,
      2,
      3,
      1,
      2,
      3,
      1,
      2,
      3,
      1,
      2,
      3,
      1,
      2,
      3,
      1,
      2,
      3,
      1,
      2,
      3,
      1,
      2,
      3,
      1,
      2,
      3,
      1,
      2,
      3,
      1,
      2,
      3,
      1,
      2,
      3,
      1,
      2,
      3,
      1,
      2,
      3,
      1,
      2,
      3,
      1,
      2,
      3,
      1,
      2,
      3,
      1,
      2,
      3,
      1,
      2,
      3,
      1,
      2,
      3,
      1,
      2,
      3,
      2,
      3,
      1
    ],
    "transitions": [
      -1514739600,
      -1343149200,
      -1234807200,
      -1220461200,
      -1207159200,
      -1191344400,
      828864000,
      846399600,
      860313600,
      877849200,
      891766800,
      909302400,
      923216400,
      941356800,
      954666000,
      972806400,
      989139600,
      1001836800,
      1018170000,
      1035705600,
      1049619600,
      1067155200,
      1081069200,
      1099209600,
      1112518800,
      1130659200,
      1143968400,
      1162108800,
      1175418000,
      1193558400,
      1207472400,
      1225008000,
      1238922000,
      1256457600,
      1268557200,
      1289116800,
      1300006800,
      1320566400,
      1331456400,
      1352016000,
      1362906000,
      1383465600,
      1394355600,
      1414915200,
      1425805200,
      1446364800,
      1457859600,
      1478419200,
      1489309200,
      1509868800,
      1520758800,
      1541318400,
      1552208400,
      1572768000,
      1583658000,
      1604217600,
      1615712400,
      1636272000,
      1647162000,
      1667116800,
      1669788000
    ],
    "types": [
      {
        "offset": -25556
      },
      {
        "offset": -25200
      },
      {
        "offset": -21600
      },
      {
        "offset": -21600
      },
      {
        "offset": -18000
      }
    ]
  }
}