{
  "ids": [
    "pacific/tongatapu"
  ],
  "tzif": {
    "posix": {
      "abbr": "+13",
      "offset": 46800,
      "transition": null
    },
    "transition_types": [
      1,
      2,
      3,
      2,
      3,
      2,
      3,
      2,
      3,
      2
    ],
    "transitions": [
      -767189952,
      -284041200,
      939214800,
      953384400,
      973342800,
      980596800,
      1004792400,
      1012046400,
      1478350800,
      1484398800
    ],
    "types": [
      {
        "offset": 44352
      },
      {
        "offset": 44400
      },
      {
        "offset": 46800
      },
      {
        "offset": 50400
      }
    ]
  }
}