{
  "ids": [
    "arctic/longyearbyen",
    "atlantic/jan_mayen",
    "europe/berlin",
    "europe/copenhagen",
    "europe/oslo",
    "europe/stockholm"
  ],
  "tzif": {
    "posix": {
      "abbr": "CET",
      "offset": 3600,
      "transition": {
        "abbr": "CEST",
        "end": {
          "date": {
            "day": null,
            "kind": "MonthWeekDay",
            "mwd": [
              10,
              5,
              0
            ]
          },
          "time": 10800
        },
        "savings": 3600,
        "start": {
          "date": {
            "day": null,
            "kind": "MonthWeekDay",
            "mwd": [
              3,
              5,
              0
            ]
          },
          "time": 7200
        }
      }
    },
    "transition_types": [
      1,
      2,
      1,
      2,
      1,
      2,
      1,
      2,
      1,
      2,
      1,
      2,
      1,
      2,
      3,
      2,
      1,
      2,
      1,
      2,
      3,
      2,
      1,
      2,
      1,
      2,
      1,
      2,
      1,
      2,
      1,
      2,
      1,
      2,
      1,
      2,
      1,
      2,
      1,
      2,
      1,
      2,
      1,
      2,
      1,
      2,
      1,
      2,
      1,
      2,
      1,
      2,
      1,
      2,
      1,
      2,
      1,
      2,
      1,
      2,
      1
    ],
    "transitions": [
      -2422054408,
      -1693706400,
      -1680483600,
      -1663455600,
      -1650150000,
      -1632006000,
      -1618700400,
      -938905200,
      -857257200,
      -844556400,
      -828226800,
      -812502000,
      -796777200,
      -781052400,
      -776563200,
      -765936000,
      -761180400,
      -748479600,
      -733273200,
      -717631200,
      -714610800,
      -710380800,
      -701910000,
      -684975600,
      -670460400,
      -654130800,
      -639010800,
      323830800,
      338950800,
      354675600,
      370400400,
      386125200,
      401850000,
      417574800,
      433299600,
      449024400,
      465354000,
      481078800,
      496803600,
      512528400,
      528253200,
      543978000,
      559702800,
      575427600,
      591152400,
      606877200,
      622602000,
      638326800,
      654656400,
      670381200,
      686106000,
      701830800,
      717555600,
      733280400,
      749005200,
      764730000,
      780454800,
      796179600,
      811904400,
      828234000,
      846378000
    ],
    "types": [
      {
        "offset": 3208
      },
      {
        "offset": 3600
      },
      {
        "offset": 7200
      },
      {
        "offset": 10800
      }
    ]
  }
}